[
    {
        "id": {
            "idValue": "forest-rangers"
        },
        "name": "Forest Rangers",
        "memberIds": [
            {
                "idValue": "forest-ranger-anna"
            },
            {
                "idValue": "forest-ranger-barry"
            },
            {
                "idValue": "forest-ranger-caroline"
            }
        ],
        "projectBaseInfo": {
            "serviceId": "github",
            "projectBaseProperties": {
                "user": "Kroetz",
                "repository": "forestRangersRepo"
            }
        }
    },
    {
        "id": {
            "idValue": "coast-guard"
        },
        "name": "Coast Guard",
        "memberIds": [
            {
                "idValue": "coast-guard-alice"
            },
            {
                "idValue": "coast-guard-ben"
            },
            {
                "idValue": "coast-guard-charlie"
            }
        ],
        "projectBaseInfo": {
            "serviceId": "github",
            "projectBaseProperties": {
                "user": "Kroetz",
                "repository": "coastGuardRepo"
            }
        }
    },
    {
        "id": {
            "idValue": "fire-fighters"
        },
        "name": "Fire Fighters",
        "memberIds": [
            {
                "idValue": "fire-fighter-carlos"
            },
            {
                "idValue": "fire-fighter-bruce"
            },
            {
                "idValue": "fire-fighter-anthony"
            }
        ],
        "projectBaseInfo": {
            "serviceId": "github",
            "projectBaseProperties": {
                "user": "Kroetz",
                "repository": "fireFightersRepo"
            }
        }
    }
]